magen_utils-1.2a3.dist-info/DESCRIPTION.rst
magen_utils-1.2a3.dist-info/METADATA
magen_utils-1.2a3.dist-info/RECORD
magen_utils-1.2a3.dist-info/WHEEL
magen_utils-1.2a3.dist-info/metadata.json
magen_utils-1.2a3.dist-info/top_level.txt
magen_utils_apis/__init__.py
magen_utils_apis/compare_utils.py
magen_utils_apis/datetime_api.py
magen_utils_apis/dd_events_wrapper.py
magen_utils_apis/decorators_api.py
magen_utils_apis/domain_resolver.py
magen_utils_apis/magen_flask_response.py
magen_utils_apis/parse_utils.py
magen_utils_apis/singleton_meta.py
